{
    "example_source": [
        "▁我还",
        "澄清",
        "了",
        "在该",
        "会议上",
        "提出的",
        "若干",
        "事项",
        "。"
    ],
    "example_target": [
        "<s>",
        "▁i",
        "▁was",
        "▁able",
        "▁to",
        "▁provide",
        "▁clarification",
        "▁on",
        "▁some",
        "▁of",
        "▁the",
        "▁matters",
        "▁which",
        "▁were",
        "▁raised",
        "▁at",
        "▁that",
        "▁meeting",
        ".",
        "</s>"
    ],
    "hypotheses": [
        {
            "hypothesis": [
                "▁i",
                "▁also",
                "▁wish",
                "▁to",
                "▁clarify",
                "▁a",
                "▁number",
                "▁of",
                "▁matters",
                "▁raised",
                "▁at",
                "▁the",
                "▁conference",
                "."
            ],
            "score": -7.5345458984375
        },
        {
            "hypothesis": [
                "▁i",
                "▁would",
                "▁also",
                "▁like",
                "▁to",
                "▁clarify",
                "▁a",
                "▁number",
                "▁of",
                "▁matters",
                "▁raised",
                "▁at",
                "▁the",
                "▁conference",
                "."
            ],
            "score": -7.6968488693237305
        },
        {
            "hypothesis": [
                "▁i",
                "▁would",
                "▁also",
                "▁like",
                "▁to",
                "▁clarify",
                "▁a",
                "▁number",
                "▁of",
                "▁matters",
                "▁raised",
                "▁at",
                "▁the",
                "▁meeting",
                "."
            ],
            "score": -8.128560066223145
        },
        {
            "hypothesis": [
                "▁i",
                "▁also",
                "▁wish",
                "▁to",
                "▁clarify",
                "▁a",
                "▁number",
                "▁of",
                "▁matters",
                "▁that",
                "▁had",
                "▁been",
                "▁made",
                "▁at",
                "▁the",
                "▁conference",
                "."
            ],
            "score": -8.90767765045166
        },
        {
            "hypothesis": [
                "▁i",
                "▁also",
                "▁wish",
                "▁to",
                "▁clarify",
                "▁a",
                "▁number",
                "▁of",
                "▁matters",
                "▁that",
                "▁had",
                "▁been",
                "▁raised",
                "▁at",
                "▁the",
                "▁conference",
                "."
            ],
            "score": -8.966475486755371
        },
        {
            "hypothesis": [
                "▁i",
                "▁would",
                "▁also",
                "▁like",
                "▁to",
                "▁clarify",
                "▁a",
                "▁number",
                "▁of",
                "▁matters",
                "▁that",
                "▁had",
                "▁been",
                "▁made",
                "▁at",
                "▁the",
                "▁conference",
                "."
            ],
            "score": -9.02545166015625
        },
        {
            "hypothesis": [
                "▁i",
                "▁would",
                "▁also",
                "▁like",
                "▁to",
                "▁clarify",
                "▁a",
                "▁number",
                "▁of",
                "▁matters",
                "▁that",
                "▁had",
                "▁been",
                "▁raised",
                "▁at",
                "▁the",
                "▁conference",
                "."
            ],
            "score": -9.131062507629395
        },
        {
            "hypothesis": [
                "▁i",
                "▁also",
                "▁wish",
                "▁to",
                "▁clarify",
                "▁a",
                "▁number",
                "▁of",
                "▁matters",
                "▁that",
                "▁have",
                "▁been",
                "▁made",
                "▁at",
                "▁the",
                "▁conference",
                "."
            ],
            "score": -9.159839630126953
        },
        {
            "hypothesis": [
                "▁i",
                "▁would",
                "▁also",
                "▁like",
                "▁to",
                "▁clarify",
                "▁a",
                "▁number",
                "▁of",
                "▁matters",
                "▁that",
                "▁have",
                "▁been",
                "▁made",
                "▁at",
                "▁the",
                "▁conference",
                "."
            ],
            "score": -9.166841506958008
        },
        {
            "hypothesis": [
                "▁i",
                "▁would",
                "▁also",
                "▁like",
                "▁to",
                "▁clarify",
                "▁a",
                "▁number",
                "▁of",
                "▁matters",
                "▁that",
                "▁have",
                "▁been",
                "▁raised",
                "▁at",
                "▁the",
                "▁conference",
                "."
            ],
            "score": -9.346562385559082
        }
    ],
    "diagnostic_info": "eyJ0IjogIjIwMjUtMTEtMjNUMTA6MjA6NDAuNzQ2MzI4IiwgImgiOiAiYXV0b2RsLWNvbnRhaW5lci0wMjRiNGY4YWE3LWU3NWIyYTdjIiwgInUiOiAicm9vdCJ9"
}