{
    "example_source": [
        "▁我还",
        "澄清",
        "了",
        "在该",
        "会议上",
        "提出的",
        "若干",
        "事项",
        "。"
    ],
    "example_target": [
        "<s>",
        "▁i",
        "▁was",
        "▁able",
        "▁to",
        "▁provide",
        "▁clarification",
        "▁on",
        "▁some",
        "▁of",
        "▁the",
        "▁matters",
        "▁which",
        "▁were",
        "▁raised",
        "▁at",
        "▁that",
        "▁meeting",
        ".",
        "</s>"
    ],
    "hypotheses": [
        {
            "hypothesis": [
                "▁i",
                "▁also",
                "▁clarified",
                "▁a",
                "▁number",
                "▁of",
                "▁matters",
                "▁raised",
                "▁at",
                "▁the",
                "▁conference",
                "."
            ],
            "score": -6.634541988372803
        },
        {
            "hypothesis": [
                "▁i",
                "▁would",
                "▁also",
                "▁like",
                "▁to",
                "▁clarify",
                "▁a",
                "▁number",
                "▁of",
                "▁matters",
                "▁raised",
                "▁at",
                "▁the",
                "▁conference",
                "."
            ],
            "score": -7.1113080978393555
        },
        {
            "hypothesis": [
                "▁i",
                "▁would",
                "▁also",
                "▁like",
                "▁to",
                "▁clarify",
                "▁a",
                "▁number",
                "▁of",
                "▁matters",
                "▁raised",
                "▁at",
                "▁the",
                "▁meeting",
                "."
            ],
            "score": -7.530954837799072
        },
        {
            "hypothesis": [
                "▁i",
                "▁would",
                "▁also",
                "▁like",
                "▁to",
                "▁clarify",
                "▁a",
                "▁number",
                "▁of",
                "▁matters",
                "▁made",
                "▁at",
                "▁the",
                "▁conference",
                "."
            ],
            "score": -7.907111167907715
        },
        {
            "hypothesis": [
                "▁i",
                "▁would",
                "▁also",
                "▁like",
                "▁to",
                "▁clarify",
                "▁a",
                "▁number",
                "▁of",
                "▁matters",
                "▁that",
                "▁had",
                "▁been",
                "▁raised",
                "▁at",
                "▁the",
                "▁conference",
                "."
            ],
            "score": -8.618734359741211
        },
        {
            "hypothesis": [
                "▁i",
                "▁would",
                "▁also",
                "▁like",
                "▁to",
                "▁clarify",
                "▁a",
                "▁number",
                "▁of",
                "▁matters",
                "▁that",
                "▁were",
                "▁made",
                "▁at",
                "▁the",
                "▁conference",
                "."
            ],
            "score": -8.725444793701172
        },
        {
            "hypothesis": [
                "▁i",
                "▁would",
                "▁also",
                "▁like",
                "▁to",
                "▁clarify",
                "▁a",
                "▁number",
                "▁of",
                "▁matters",
                "▁that",
                "▁had",
                "▁been",
                "▁made",
                "▁at",
                "▁the",
                "▁conference",
                "."
            ],
            "score": -8.729446411132812
        },
        {
            "hypothesis": [
                "▁i",
                "▁would",
                "▁also",
                "▁like",
                "▁to",
                "▁clarify",
                "▁a",
                "▁number",
                "▁of",
                "▁matters",
                "▁that",
                "▁have",
                "▁been",
                "▁raised",
                "▁at",
                "▁the",
                "▁conference",
                "."
            ],
            "score": -9.051788330078125
        },
        {
            "hypothesis": [
                "▁i",
                "▁would",
                "▁also",
                "▁like",
                "▁to",
                "▁clarify",
                "▁a",
                "▁number",
                "▁of",
                "▁matters",
                "▁that",
                "▁had",
                "▁been",
                "▁raised",
                "▁at",
                "▁the",
                "▁meeting",
                "."
            ],
            "score": -9.08856201171875
        },
        {
            "hypothesis": [
                "▁i",
                "▁would",
                "▁also",
                "▁like",
                "▁to",
                "▁clarify",
                "▁a",
                "▁number",
                "▁of",
                "▁matters",
                "▁that",
                "▁have",
                "▁been",
                "▁made",
                "▁at",
                "▁the",
                "▁conference",
                "."
            ],
            "score": -9.11618709564209
        }
    ],
    "diagnostic_info": "eyJ0IjogIjIwMjUtMTEtMjNUMTA6MjI6NDIuNDA1NTc4IiwgImgiOiAiYXV0b2RsLWNvbnRhaW5lci0wMjRiNGY4YWE3LWU3NWIyYTdjIiwgInUiOiAicm9vdCJ9"
}